logingov/__init__.py
logingov/apps.py
logingov/helpers.py
logingov/oidc.py
logingov/management/__init__.py
logingov/management/commands/__init__.py
logingov/management/commands/logingov_pk_to_file.py
logingov/settings/__init__.py
logingov/settings/oidc_settings.py
logingov/tests/__init__.py
logingov/tests/mock_server.py
logingov/tests/test_oidc.py
logingov/tests/test_oidc_settings.py
py_logingov_client-0.0.2.dist-info/LICENSE
py_logingov_client-0.0.2.dist-info/METADATA
py_logingov_client-0.0.2.dist-info/WHEEL
py_logingov_client-0.0.2.dist-info/top_level.txt
py_logingov_client-0.0.2.dist-info/RECORD
